fizzbuzz_draw/__init__.py
fizzbuzz_draw/__main__.py
fizzbuzz_draw/app.py
fizzbuzz_draw/nested_collections.py
fizzbuzz_draw/setup_mg.py
fizzbuzz_draw-1.0.14.dist-info/LICENSE
fizzbuzz_draw-1.0.14.dist-info/METADATA
fizzbuzz_draw-1.0.14.dist-info/WHEEL
fizzbuzz_draw-1.0.14.dist-info/entry_points.txt
fizzbuzz_draw-1.0.14.dist-info/top_level.txt
fizzbuzz_draw-1.0.14.dist-info/RECORD
