Metadata-Version: 2.1
Name: fizzbuzz-draw
Version: 1.0.14
Summary: Fizzbuzz draw lolz
Author-email: Dhiyaa Al Jorf <da2863@nyu.edu>, Firas Darwish <fbd2014@nyu.edu>, Shubhi Upadhyay <su2132@nyu.edu>
License: GNU GENERAL PUBLIC LICENSE
Project-URL: Homepage, https://github.com/software-students-spring2024/5-final-project-spring-2024-team-fizzbuzz-final
Project-URL: Repository, https://github.com/software-students-spring2024/5-final-project-spring-2024-team-fizzbuzz-final.git
Project-URL: Bug Tracker, https://github.com/software-students-spring2024/5-final-project-spring-2024-team-fizzbuzz-final/issues
Keywords: draw,scribble,fizzbuzz
Classifier: Programming Language :: Python :: 3
Classifier: Intended Audience :: Education
Classifier: License :: OSI Approved :: GNU General Public License v3 (GPLv3)
Classifier: Operating System :: OS Independent
Requires-Python: >=3.9
License-File: LICENSE
Provides-Extra: dev
Requires-Dist: pytest ; extra == 'dev'
